{"cameraMode":{"drawMode":0,"name":"Shaded","section":"Shading Mode"},"sceneLighting":true,"audioPlay":false,"sceneViewState":{"showFog":true,"showMaterialUpdate":false,"showSkybox":true,"showFlares":true,"showImageEffects":true,"showParticleSystems":true},"in2DMode":false,"pivot":{"x":-56.34306335449219,"y":-8.323119163513184,"z":5.770989894866943},"rotation":{"x":0.24575932323932649,"y":0.7239826321601868,"z":-0.5612003803253174,"w":0.31709298491477969},"size":120.73482513427735,"orthographic":false}